pysqlgrid/__init__.py
pysqlgrid/pysqlgrid.py
pysqlgrid-1.0.1.dist-info/METADATA
pysqlgrid-1.0.1.dist-info/RECORD
pysqlgrid-1.0.1.dist-info/WHEEL
pysqlgrid-1.0.1.dist-info/top_level.txt
